kmeanssa_ng-0.6.0.dist-info/METADATA
kmeanssa_ng-0.6.0.dist-info/WHEEL
kmeanssa_ng-0.6.0.dist-info/entry_points.txt
kmeanssa_ng-0.6.0.dist-info/licenses/LICENSE
kmeanssa_ng/__init__.py
kmeanssa_ng/core/__init__.py
kmeanssa_ng/core/abstract.py
kmeanssa_ng/core/metrics.py
kmeanssa_ng/core/parallel.py
kmeanssa_ng/core/simulated_annealing.py
kmeanssa_ng/core/strategies/__init__.py
kmeanssa_ng/core/strategies/initialization.py
kmeanssa_ng/core/strategies/robustification.py
kmeanssa_ng/core/strategies/sampling.py
kmeanssa_ng/quantum_graph/__init__.py
kmeanssa_ng/quantum_graph/__pycache__/space._batch_distances_numba-16.py312.1.nbc
kmeanssa_ng/quantum_graph/__pycache__/space._batch_distances_numba-16.py312.2.nbc
kmeanssa_ng/quantum_graph/__pycache__/space._batch_distances_numba-16.py312.nbi
kmeanssa_ng/quantum_graph/__pycache__/space._batch_distances_numba-16.py39.1.nbc
kmeanssa_ng/quantum_graph/__pycache__/space._batch_distances_numba-16.py39.2.nbc
kmeanssa_ng/quantum_graph/__pycache__/space._batch_distances_numba-16.py39.nbi
kmeanssa_ng/quantum_graph/__pycache__/space._batch_distances_numba-18.py39.1.nbc
kmeanssa_ng/quantum_graph/__pycache__/space._batch_distances_numba-18.py39.2.nbc
kmeanssa_ng/quantum_graph/__pycache__/space._batch_distances_numba-18.py39.nbi
kmeanssa_ng/quantum_graph/__pycache__/space._batch_distances_numba-20.py312.1.nbc
kmeanssa_ng/quantum_graph/__pycache__/space._batch_distances_numba-20.py312.2.nbc
kmeanssa_ng/quantum_graph/__pycache__/space._batch_distances_numba-20.py312.3.nbc
kmeanssa_ng/quantum_graph/__pycache__/space._batch_distances_numba-20.py312.4.nbc
kmeanssa_ng/quantum_graph/__pycache__/space._batch_distances_numba-20.py312.nbi
kmeanssa_ng/quantum_graph/__pycache__/space._batch_distances_numba-21.py312.1.nbc
kmeanssa_ng/quantum_graph/__pycache__/space._batch_distances_numba-21.py312.2.nbc
kmeanssa_ng/quantum_graph/__pycache__/space._batch_distances_numba-21.py312.nbi
kmeanssa_ng/quantum_graph/__pycache__/space._calculate_energy_numba-93.py312.1.nbc
kmeanssa_ng/quantum_graph/__pycache__/space._calculate_energy_numba-93.py312.nbi
kmeanssa_ng-0.6.0.dist-info/RECORD
