Metadata-Version: 2.1
Name: kmeanssa-ng
Version: 0.6.0
Summary: K-means clustering on quantum graphs and metric spaces using simulated annealing
Keywords: clustering,k-means,metric-spaces,quantum-graphs,simulated-annealing
Author-Email: Nicolas Klutchnikoff <nicolas.klutchnikoff@univ-rennes2.fr>, Ioana Gavra <ioana.gavra@univ-rennes2.fr>
License: MIT
Classifier: Development Status :: 3 - Alpha
Classifier: Intended Audience :: Science/Research
Classifier: License :: OSI Approved :: MIT License
Classifier: Programming Language :: Python :: 3
Classifier: Programming Language :: Python :: 3.10
Classifier: Programming Language :: Python :: 3.11
Classifier: Programming Language :: Python :: 3.12
Classifier: Topic :: Scientific/Engineering :: Mathematics
Requires-Python: >=3.10
Requires-Dist: networkx>=3.0
Requires-Dist: numba>=0.60.0
Requires-Dist: numpy>=1.24.0
Requires-Dist: pandas>=2.0.0
Requires-Dist: scikit-learn>=1.3.0
Requires-Dist: geomstats>=2.8.0
Provides-Extra: plot
Requires-Dist: matplotlib>=3.10.7; extra == "plot"
